PyQt5-stubs/__init__.pyi
PyQt5-stubs/QAxContainer/_QAxBase.pyi
PyQt5-stubs/QAxContainer/_QAxObject.pyi
PyQt5-stubs/QAxContainer/_QAxWidget.pyi
PyQt5-stubs/QAxContainer/__init__.pyi
PyQt5-stubs/QAxContainer/_functions.pyi
PyQt5-stubs/QtBluetooth/_QBluetooth.pyi
PyQt5-stubs/QtBluetooth/_QBluetoothAddress.pyi
PyQt5-stubs/QtBluetooth/_QBluetoothDeviceDiscoveryAgent.pyi
PyQt5-stubs/QtBluetooth/_QBluetoothDeviceInfo.pyi
PyQt5-stubs/QtBluetooth/_QBluetoothHostInfo.pyi
PyQt5-stubs/QtBluetooth/_QBluetoothLocalDevice.pyi
PyQt5-stubs/QtBluetooth/_QBluetoothServer.pyi
PyQt5-stubs/QtBluetooth/_QBluetoothServiceDiscoveryAgent.pyi
PyQt5-stubs/QtBluetooth/_QBluetoothServiceInfo.pyi
PyQt5-stubs/QtBluetooth/_QBluetoothSocket.pyi
PyQt5-stubs/QtBluetooth/_QBluetoothTransferManager.pyi
PyQt5-stubs/QtBluetooth/_QBluetoothTransferReply.pyi
PyQt5-stubs/QtBluetooth/_QBluetoothTransferRequest.pyi
PyQt5-stubs/QtBluetooth/_QBluetoothUuid.pyi
PyQt5-stubs/QtBluetooth/_QLowEnergyAdvertisingData.pyi
PyQt5-stubs/QtBluetooth/_QLowEnergyAdvertisingParameters.pyi
PyQt5-stubs/QtBluetooth/_QLowEnergyCharacteristic.pyi
PyQt5-stubs/QtBluetooth/_QLowEnergyCharacteristicData.pyi
PyQt5-stubs/QtBluetooth/_QLowEnergyConnectionParameters.pyi
PyQt5-stubs/QtBluetooth/_QLowEnergyController.pyi
PyQt5-stubs/QtBluetooth/_QLowEnergyDescriptor.pyi
PyQt5-stubs/QtBluetooth/_QLowEnergyDescriptorData.pyi
PyQt5-stubs/QtBluetooth/_QLowEnergyService.pyi
PyQt5-stubs/QtBluetooth/_QLowEnergyServiceData.pyi
PyQt5-stubs/QtBluetooth/__init__.pyi
PyQt5-stubs/QtBluetooth/_functions.pyi
PyQt5-stubs/QtCore/_QAbstractAnimation.pyi
PyQt5-stubs/QtCore/_QAbstractEventDispatcher.pyi
PyQt5-stubs/QtCore/_QAbstractItemModel.pyi
PyQt5-stubs/QtCore/_QAbstractListModel.pyi
PyQt5-stubs/QtCore/_QAbstractNativeEventFilter.pyi
PyQt5-stubs/QtCore/_QAbstractProxyModel.pyi
PyQt5-stubs/QtCore/_QAbstractState.pyi
PyQt5-stubs/QtCore/_QAbstractTableModel.pyi
PyQt5-stubs/QtCore/_QAbstractTransition.pyi
PyQt5-stubs/QtCore/_QAnimationGroup.pyi
IceSpringPySideStubs_PyQt5-1.3.1.dist-info/METADATA
IceSpringPySideStubs_PyQt5-1.3.1.dist-info/WHEEL
IceSpringPySideStubs_PyQt5-1.3.1.dist-info/top_level.txt
IceSpringPySideStubs_PyQt5-1.3.1.dist-info/RECORD
